README.md
flake8_expandtab.py
setup.py
flake8_expandtab.egg-info/PKG-INFO
flake8_expandtab.egg-info/SOURCES.txt
flake8_expandtab.egg-info/dependency_links.txt
flake8_expandtab.egg-info/entry_points.txt
flake8_expandtab.egg-info/top_level.txt