Metadata-Version: 1.1
Name: flake8-expandtab
Version: 0.2
Summary: flake8 for tab junkies
Home-page: https://www.github.com/hyperair/flake8-expandtab
Author: Chow Loong Jin
Author-email: hyperair@debian.org
License: MIT
Platform: UNKNOWN
Classifier: Framework :: Flake8
Classifier: Intended Audience :: Developers
Classifier: Development Status :: 4 - Beta
Classifier: License :: OSI Approved :: MIT License
Classifier: Programming Language :: Python
Classifier: Programming Language :: Python :: 2
Classifier: Programming Language :: Python :: 3
Classifier: Topic :: Software Development :: Libraries :: Python Modules
Classifier: Topic :: Software Development :: Quality Assurance
Classifier: Operating System :: OS Independent
